Luxbeam/__init__.py
Luxbeam/luxbeam.py
Luxbeam/luxbeam_enums.py
Luxbeam/sample.py
Luxbeam/sequencer.py
Luxbeam-0.1.2.dist-info/METADATA
Luxbeam-0.1.2.dist-info/WHEEL
Luxbeam-0.1.2.dist-info/top_level.txt
Luxbeam-0.1.2.dist-info/RECORD
